MANIFEST.in
README.md
README.rst
setup.py
src/armorvise.egg-info/PKG-INFO
src/armorvise.egg-info/SOURCES.txt
src/armorvise.egg-info/dependency_links.txt
src/armorvise.egg-info/entry_points.txt
src/armorvise.egg-info/top_level.txt
src/process/__init__.py
src/process/__main__.py
src/process/armor.py
src/process/ext/__init__.py
src/process/ext/conf.json
src/process/libs/__init__.py
src/process/libs/conf.py
src/process/libs/console.py
src/process/libs/daemon.py
src/process/libs/util.py