Metadata-Version: 1.0
Name: armorvise
Version: 1.1.3
Summary: A daemon tool on linux
Home-page: https://github.com/numberwolf/armorvise
Author: changyanlong
Author-email: porschegt23@foxmail.com
License: MIT
Keywords: armorvise,daemon,armor,changyanlong
Platform: L
Platform: i
Platform: n
Platform: u
Platform: x
